CHANGES.rst
CONTRIBUTORS.rst
DEVELOP.rst
LICENSE.rst
MANIFEST.in
README.rst
setup.cfg
setup.py
docs/index.rst
src/collective/__init__.py
src/collective.iconifiednavigation.egg-info/PKG-INFO
src/collective.iconifiednavigation.egg-info/SOURCES.txt
src/collective.iconifiednavigation.egg-info/dependency_links.txt
src/collective.iconifiednavigation.egg-info/entry_points.txt
src/collective.iconifiednavigation.egg-info/namespace_packages.txt
src/collective.iconifiednavigation.egg-info/not-zip-safe
src/collective.iconifiednavigation.egg-info/requires.txt
src/collective.iconifiednavigation.egg-info/top_level.txt
src/collective/iconifiednavigation/__init__.py
src/collective/iconifiednavigation/configure.zcml
src/collective/iconifiednavigation/interfaces.py
src/collective/iconifiednavigation/permissions.zcml
src/collective/iconifiednavigation/setuphandlers.py
src/collective/iconifiednavigation/testing.py
src/collective/iconifiednavigation/upgrades.py
src/collective/iconifiednavigation/upgrades.zcml
src/collective/iconifiednavigation/behaviors/__init__.py
src/collective/iconifiednavigation/behaviors/behaviors.py
src/collective/iconifiednavigation/behaviors/configure.zcml
src/collective/iconifiednavigation/browser/__init__.py
src/collective/iconifiednavigation/browser/configure.zcml
src/collective/iconifiednavigation/browser/navigation.py
src/collective/iconifiednavigation/browser/overrides/.gitkeep
src/collective/iconifiednavigation/browser/static/.gitkeep
src/collective/iconifiednavigation/locales/collective.iconifiednavigation.pot
src/collective/iconifiednavigation/locales/update.sh
src/collective/iconifiednavigation/locales/fr/LC_MESSAGES/collective.iconifiednavigation.po
src/collective/iconifiednavigation/locales/nl/LC_MESSAGES/collective.iconifiednavigation.po
src/collective/iconifiednavigation/profiles/default/browserlayer.xml
src/collective/iconifiednavigation/profiles/default/catalog.xml
src/collective/iconifiednavigation/profiles/default/metadata.xml
src/collective/iconifiednavigation/profiles/default/registry.xml
src/collective/iconifiednavigation/profiles/default/rolemap.xml
src/collective/iconifiednavigation/profiles/uninstall/browserlayer.xml
src/collective/iconifiednavigation/tests/__init__.py
src/collective/iconifiednavigation/tests/test_robot.py
src/collective/iconifiednavigation/tests/test_setup.py
src/collective/iconifiednavigation/tests/robot/test_example.robot
src/collective/iconifiednavigation/viewlets/__init__.py
