Metadata-Version: 2.1
Name: collective.iconifiednavigation
Version: 1.0.1
Summary: Add content icons in portal_tabs menu
Home-page: https://pypi.python.org/pypi/collective.iconifiednavigation
Author: Sebastien Sirtoli
Author-email: info@affinitic.be
License: GPL version 2
Keywords: Python Plone
Platform: UNKNOWN
Classifier: Environment :: Web Environment
Classifier: Framework :: Plone
Classifier: Framework :: Plone :: 5.0
Classifier: Framework :: Plone :: 5.1
Classifier: Programming Language :: Python
Classifier: Programming Language :: Python :: 2.7
Classifier: Operating System :: OS Independent
Classifier: License :: OSI Approved :: GNU General Public License v2 (GPLv2)
Provides-Extra: test
